upstream/__init__.py
upstream/auth.py
upstream/campaigns.py
upstream/ckan.py
upstream/client.py
upstream/data.py
upstream/exceptions.py
upstream/measurements.py
upstream/py.typed
upstream/sensors.py
upstream/stations.py
upstream/utils.py
upstream_sdk-1.0.2.dist-info/licenses/LICENSE
upstream_sdk-1.0.2.dist-info/METADATA
upstream_sdk-1.0.2.dist-info/WHEEL
upstream_sdk-1.0.2.dist-info/entry_points.txt
upstream_sdk-1.0.2.dist-info/top_level.txt
upstream_sdk-1.0.2.dist-info/RECORD
