Metadata-Version: 2.4
Name: upstream-sdk
Version: 1.0.2
Summary: Python SDK for Upstream environmental sensor data platform and CKAN integration
Author-email: In-For-Disaster-Analytics Team <info@tacc.utexas.edu>
Maintainer-email: In-For-Disaster-Analytics Team <info@tacc.utexas.edu>
License: MIT
Project-URL: Homepage, https://github.com/In-For-Disaster-Analytics/upstream-python-sdk
Project-URL: Documentation, https://upstream-python-sdk.readthedocs.io
Project-URL: Repository, https://github.com/In-For-Disaster-Analytics/upstream-python-sdk
Project-URL: Issues, https://github.com/In-For-Disaster-Analytics/upstream-python-sdk/issues
Project-URL: Changelog, https://github.com/In-For-Disaster-Analytics/upstream-python-sdk/blob/main/CHANGELOG.md
Keywords: environmental,sensors,data,api,ckan,upstream
Classifier: Development Status :: 4 - Beta
Classifier: Intended Audience :: Science/Research
Classifier: License :: OSI Approved :: MIT License
Classifier: Operating System :: OS Independent
Classifier: Programming Language :: Python :: 3
Classifier: Programming Language :: Python :: 3.9
Classifier: Programming Language :: Python :: 3.10
Classifier: Programming Language :: Python :: 3.11
Classifier: Programming Language :: Python :: 3.12
Classifier: Topic :: Scientific/Engineering
Classifier: Topic :: Scientific/Engineering :: Atmospheric Science
Classifier: Topic :: Scientific/Engineering :: GIS
Classifier: Topic :: Internet :: WWW/HTTP :: Dynamic Content
Classifier: Topic :: Software Development :: Libraries :: Python Modules
Requires-Python: >=3.9
License-File: LICENSE
Requires-Dist: requests>=2.25.0
Requires-Dist: pyyaml>=6.0
Requires-Dist: python-dateutil>=2.8.0
Requires-Dist: typing-extensions>=4.0.0; python_version < "3.10"
Requires-Dist: pydantic>=2.0.0
Requires-Dist: urllib3>=1.25.3
Requires-Dist: upstream-api-client>=0.1.8
Provides-Extra: dev
Requires-Dist: pytest>=7.0.0; extra == "dev"
Requires-Dist: pytest-cov>=4.0.0; extra == "dev"
Requires-Dist: pytest-mock>=3.6.0; extra == "dev"
Requires-Dist: pytest-asyncio>=0.21.0; extra == "dev"
Requires-Dist: black>=22.0.0; extra == "dev"
Requires-Dist: flake8>=5.0.0; extra == "dev"
Requires-Dist: mypy>=1.0.0; extra == "dev"
Requires-Dist: pre-commit>=2.20.0; extra == "dev"
Requires-Dist: tox>=4.0.0; extra == "dev"
Requires-Dist: sphinx>=5.0.0; extra == "dev"
Requires-Dist: sphinx-rtd-theme>=1.2.0; extra == "dev"
Requires-Dist: twine>=4.0.0; extra == "dev"
Requires-Dist: build>=0.8.0; extra == "dev"
Provides-Extra: data
Requires-Dist: pandas>=1.3.0; extra == "data"
Requires-Dist: numpy>=1.20.0; extra == "data"
Provides-Extra: examples
Requires-Dist: jupyter>=1.0.0; extra == "examples"
Requires-Dist: matplotlib>=3.5.0; extra == "examples"
Requires-Dist: seaborn>=0.11.0; extra == "examples"
Provides-Extra: all
Requires-Dist: upstream-sdk[data,dev,examples]; extra == "all"
Dynamic: license-file
